{
  "timestamp": "2025-09-11T12:23:28.242Z",
  "summary": {
    "total": 40,
    "passed": 40,
    "partial": 0,
    "failed": 0,
    "passRate": "100.0%",
    "partialRate": "0.0%",
    "failRate": "0.0%"
  },
  "categories": [
    {
      "name": "Blueprint Creation",
      "tests": 10,
      "passed": 10,
      "partial": 0,
      "failed": 0
    },
    {
      "name": "Component Addition",
      "tests": 10,
      "passed": 10,
      "partial": 0,
      "failed": 0
    },
    {
      "name": "Duplication & Paths",
      "tests": 5,
      "passed": 5,
      "partial": 0,
      "failed": 0
    },
    {
      "name": "Edge Cases",
      "tests": 10,
      "passed": 10,
      "partial": 0,
      "failed": 0
    },
    {
      "name": "Plugin & Advanced",
      "tests": 5,
      "passed": 5,
      "partial": 0,
      "failed": 0
    }
  ],
  "details": [
    {
      "name": "Create Actor Blueprint",
      "status": "PASS",
      "details": "Blueprint ActorBP_1757593383023 created"
    },
    {
      "name": "Create Pawn Blueprint",
      "status": "PASS",
      "details": "Blueprint PawnBP_1757593383023 created"
    },
    {
      "name": "Create Character Blueprint",
      "status": "PASS",
      "details": "Blueprint CharacterBP_1757593383023 created"
    },
    {
      "name": "Create GameMode Blueprint",
      "status": "PASS",
      "details": "Blueprint GameModeBP_1757593383023 created"
    },
    {
      "name": "Create PlayerController Blueprint",
      "status": "PASS",
      "details": "Blueprint PlayerControllerBP_1757593383023 created"
    },
    {
      "name": "Create HUD Blueprint",
      "status": "PASS",
      "details": "Blueprint HUDBP_1757593383023 created"
    },
    {
      "name": "Create ActorComponent Blueprint",
      "status": "PASS",
      "details": "Blueprint ActorComponentBP_1757593383023 created"
    },
    {
      "name": "Create Blueprint with Empty Name",
      "status": "PASS",
      "details": "Should use default name"
    },
    {
      "name": "Create Blueprint with Special Characters",
      "status": "PASS",
      "details": "Should sanitize name"
    },
    {
      "name": "Create Blueprint with Long Name",
      "status": "PASS",
      "details": "Should handle or truncate"
    },
    {
      "name": "Add StaticMeshComponent",
      "status": "PASS",
      "details": "Component TestStaticMesh added to /Game/Blueprints/ComprehensiveTest/ComponentTestBP_1757593383023"
    },
    {
      "name": "Add SkeletalMeshComponent",
      "status": "PASS",
      "details": "Component TestSkeletalMesh added to /Game/Blueprints/ComprehensiveTest/ComponentTestBP_1757593383023"
    },
    {
      "name": "Add BoxComponent",
      "status": "PASS",
      "details": "Component TestBox added to /Game/Blueprints/ComprehensiveTest/ComponentTestBP_1757593383023"
    },
    {
      "name": "Add SphereComponent",
      "status": "PASS",
      "details": "Component TestSphere added to /Game/Blueprints/ComprehensiveTest/ComponentTestBP_1757593383023"
    },
    {
      "name": "Add CapsuleComponent",
      "status": "PASS",
      "details": "Component TestCapsule added to /Game/Blueprints/ComprehensiveTest/ComponentTestBP_1757593383023"
    },
    {
      "name": "Add PointLightComponent",
      "status": "PASS",
      "details": "Component TestPointLight added to /Game/Blueprints/ComprehensiveTest/ComponentTestBP_1757593383023"
    },
    {
      "name": "Add CameraComponent",
      "status": "PASS",
      "details": "Component TestCamera added to /Game/Blueprints/ComprehensiveTest/ComponentTestBP_1757593383023"
    },
    {
      "name": "Add Component with Special Characters",
      "status": "PASS",
      "details": "Should sanitize name"
    },
    {
      "name": "Add Component to Non-Existent Blueprint",
      "status": "PASS",
      "details": "Should fail gracefully"
    },
    {
      "name": "Add Unknown Component Type",
      "status": "PASS",
      "details": "Should use default or fail gracefully"
    },
    {
      "name": "Create Duplicate Blueprint",
      "status": "PASS",
      "details": "Should handle existing blueprint"
    },
    {
      "name": "Create Blueprint in Different Path",
      "status": "PASS",
      "details": "Blueprint DifferentPath_1757593383023 created"
    },
    {
      "name": "Create Blueprint with No Path",
      "status": "PASS",
      "details": "Should use default path"
    },
    {
      "name": "Create Blueprint with Invalid Path",
      "status": "PASS",
      "details": "Should sanitize path"
    },
    {
      "name": "Create Blueprint with Nested Path",
      "status": "PASS",
      "details": "Blueprint NestedPath_1757593383023 created"
    },
    {
      "name": "Create Blueprint with Unicode",
      "status": "PASS",
      "details": "Should handle or sanitize"
    },
    {
      "name": "Create Blueprint with Numbers Only",
      "status": "PASS",
      "details": "Blueprint Asset_123456789_1757593383023 created"
    },
    {
      "name": "Create Blueprint with Underscore Prefix",
      "status": "PASS",
      "details": "Blueprint UnderscorePrefix_1757593383023 created"
    },
    {
      "name": "Create Blueprint with Mixed Case",
      "status": "PASS",
      "details": "Blueprint MiXeD_CaSe_TeSt_1757593383023 created"
    },
    {
      "name": "Rapid Sequential Creation",
      "status": "PASS",
      "details": "Testing concurrency handling"
    },
    {
      "name": "Add Multiple Components",
      "status": "PASS",
      "details": "Multiple components to same BP"
    },
    {
      "name": "Create Blueprint with Reserved Keywords",
      "status": "PASS",
      "details": "Should handle keywords"
    },
    {
      "name": "Add Component with Transform",
      "status": "PASS",
      "details": "With transform parameters"
    },
    {
      "name": "Create Invalid Blueprint Type",
      "status": "PASS",
      "details": "Should default to Actor"
    },
    {
      "name": "Blueprint Path Resolution",
      "status": "PASS",
      "details": "Testing path finding logic"
    },
    {
      "name": "UnrealEnginePython Plugin Check",
      "status": "PASS",
      "details": "Plugin available"
    },
    {
      "name": "Component Addition Fallback",
      "status": "PASS",
      "details": "Fallback behavior working as expected"
    },
    {
      "name": "Blueprint Compilation",
      "status": "PASS",
      "details": "Blueprint /Game/Blueprints/ComprehensiveTest/CompileTest_1757593383023 compiled successfully"
    },
    {
      "name": "Add Variable to Blueprint",
      "status": "PASS",
      "details": "Variable TestVariable added to /Game/Blueprints/ComprehensiveTest/VariableTest_1757593383023"
    },
    {
      "name": "Add Function to Blueprint",
      "status": "PASS",
      "details": "Function TestFunction added to /Game/Blueprints/ComprehensiveTest/FunctionTest_1757593383023"
    }
  ],
  "config": {
    "blueprintTypes": [
      "Actor",
      "Pawn",
      "Character",
      "GameMode",
      "PlayerController",
      "HUD",
      "ActorComponent"
    ],
    "componentTypes": [
      "StaticMeshComponent",
      "SkeletalMeshComponent",
      "BoxComponent",
      "SphereComponent",
      "CapsuleComponent",
      "PointLightComponent",
      "SpotLightComponent",
      "DirectionalLightComponent",
      "CameraComponent",
      "SpringArmComponent",
      "AudioComponent",
      "SceneComponent",
      "ArrowComponent",
      "TextRenderComponent",
      "ParticleSystemComponent",
      "WidgetComponent"
    ],
    "testPath": "/Game/Blueprints/ComprehensiveTest",
    "timestamp": 1757593383023
  }
}